{
    "book": "1 Thessalonians",
    "chapter": 4,
    "verses": [
        {
            "ref": "1 Thess 4:1",
            "function": "moral_instruction"
        },
        {
            "ref": "1 Thess 4:2",
            "function": "moral_instruction"
        },
        {
            "ref": "1 Thess 4:3",
            "function": "sexual_marital",
            "secondary": {
                "function": "theological",
                "weight": 0.25
            }
        },
        {
            "ref": "1 Thess 4:4",
            "function": "sexual_marital"
        },
        {
            "ref": "1 Thess 4:5",
            "function": "sexual_marital"
        },
        {
            "ref": "1 Thess 4:6",
            "function": "sexual_marital"
        },
        {
            "ref": "1 Thess 4:7",
            "function": "theological",
            "secondary": {
                "function": "sexual_marital",
                "weight": 0.3
            }
        },
        {
            "ref": "1 Thess 4:8",
            "function": "theological"
        },
        {
            "ref": "1 Thess 4:9",
            "function": "moral_instruction"
        },
        {
            "ref": "1 Thess 4:10",
            "function": "moral_instruction"
        },
        {
            "ref": "1 Thess 4:11",
            "function": "moral_instruction"
        },
        {
            "ref": "1 Thess 4:12",
            "function": "moral_instruction"
        },
        {
            "ref": "1 Thess 4:13",
            "function": "theological"
        },
        {
            "ref": "1 Thess 4:14",
            "function": "theological"
        },
        {
            "ref": "1 Thess 4:15",
            "function": "prophecy",
            "secondary": {
                "function": "theological",
                "weight": 0.2
            }
        },
        {
            "ref": "1 Thess 4:16",
            "function": "prophecy"
        },
        {
            "ref": "1 Thess 4:17",
            "function": "prophecy"
        },
        {
            "ref": "1 Thess 4:18",
            "function": "moral_instruction"
        }
    ],
    "stories": [
        {
            "name": "Living in Holiness: Sex, Community, and Work",
            "start": "1 Thess 4:1",
            "end": "1 Thess 4:12",
            "continues_from_previous": true,
            "continues_in_next": true,
            "morals": [
                {
                    "theme": "obey_god",
                    "weight": 2.0
                },
                {
                    "theme": "sexual_purity",
                    "weight": 1.5
                },
                {
                    "theme": "mercy",
                    "weight": 1.0
                }
            ]
        },
        {
            "name": "The Hope of the Resurrection",
            "start": "1 Thess 4:13",
            "end": "1 Thess 4:18",
            "continues_from_previous": false,
            "continues_in_next": true,
            "morals": [
                {
                    "theme": "faith_trust",
                    "weight": 2.0
                },
                {
                    "theme": "gods_power",
                    "weight": 1.5
                }
            ]
        }
    ]
}
