{
    "book": "Ezra",
    "chapter": 8,
    "verses": [
        {
            "ref": "Ezra 8:1",
            "function": "catalog"
        },
        {
            "ref": "Ezra 8:2",
            "function": "catalog"
        },
        {
            "ref": "Ezra 8:3",
            "function": "catalog"
        },
        {
            "ref": "Ezra 8:4",
            "function": "catalog"
        },
        {
            "ref": "Ezra 8:5",
            "function": "catalog"
        },
        {
            "ref": "Ezra 8:6",
            "function": "catalog"
        },
        {
            "ref": "Ezra 8:7",
            "function": "catalog"
        },
        {
            "ref": "Ezra 8:8",
            "function": "catalog"
        },
        {
            "ref": "Ezra 8:9",
            "function": "catalog"
        },
        {
            "ref": "Ezra 8:10",
            "function": "catalog"
        },
        {
            "ref": "Ezra 8:11",
            "function": "catalog"
        },
        {
            "ref": "Ezra 8:12",
            "function": "catalog"
        },
        {
            "ref": "Ezra 8:13",
            "function": "catalog"
        },
        {
            "ref": "Ezra 8:14",
            "function": "catalog"
        },
        {
            "ref": "Ezra 8:15",
            "function": "narrative"
        },
        {
            "ref": "Ezra 8:16",
            "function": "narrative"
        },
        {
            "ref": "Ezra 8:17",
            "function": "narrative"
        },
        {
            "ref": "Ezra 8:18",
            "function": "narrative",
            "secondary": {
                "function": "theological",
                "weight": 0.3
            }
        },
        {
            "ref": "Ezra 8:19",
            "function": "narrative"
        },
        {
            "ref": "Ezra 8:20",
            "function": "narrative",
            "secondary": {
                "function": "catalog",
                "weight": 0.3
            }
        },
        {
            "ref": "Ezra 8:21",
            "function": "narrative",
            "secondary": {
                "function": "moral_instruction",
                "weight": 0.2
            }
        },
        {
            "ref": "Ezra 8:22",
            "function": "narrative",
            "secondary": {
                "function": "theological",
                "weight": 0.4
            }
        },
        {
            "ref": "Ezra 8:23",
            "function": "narrative"
        },
        {
            "ref": "Ezra 8:24",
            "function": "narrative"
        },
        {
            "ref": "Ezra 8:25",
            "function": "narrative"
        },
        {
            "ref": "Ezra 8:26",
            "function": "specifications"
        },
        {
            "ref": "Ezra 8:27",
            "function": "specifications"
        },
        {
            "ref": "Ezra 8:28",
            "function": "narrative",
            "secondary": {
                "function": "theological",
                "weight": 0.3
            }
        },
        {
            "ref": "Ezra 8:29",
            "function": "narrative"
        },
        {
            "ref": "Ezra 8:30",
            "function": "narrative"
        },
        {
            "ref": "Ezra 8:31",
            "function": "narrative",
            "secondary": {
                "function": "theological",
                "weight": 0.2
            }
        },
        {
            "ref": "Ezra 8:32",
            "function": "narrative"
        },
        {
            "ref": "Ezra 8:33",
            "function": "narrative"
        },
        {
            "ref": "Ezra 8:34",
            "function": "narrative",
            "secondary": {
                "function": "specifications",
                "weight": 0.3
            }
        },
        {
            "ref": "Ezra 8:35",
            "function": "narrative",
            "secondary": {
                "function": "ritual_instruction",
                "weight": 0.4
            }
        },
        {
            "ref": "Ezra 8:36",
            "function": "narrative"
        }
    ],
    "stories": [
        {
            "name": "Ezra's Return from Babylon",
            "start": "Ezra 8:1",
            "end": "Ezra 8:36",
            "continues_from_previous": true,
            "continues_in_next": false,
            "morals": [
                {
                    "theme": "faith_trust",
                    "weight": 2.0
                },
                {
                    "theme": "gods_power",
                    "weight": 1.5
                },
                {
                    "theme": "obey_god",
                    "weight": 0.8
                }
            ]
        }
    ]
}
